ksqldb/__init__.py
ksqldb/api.py
ksqldb/client.py
ksqldb-1.0.1.dist-info/LICENSE
ksqldb-1.0.1.dist-info/METADATA
ksqldb-1.0.1.dist-info/WHEEL
ksqldb-1.0.1.dist-info/top_level.txt
ksqldb-1.0.1.dist-info/RECORD
