Metadata-Version: 2.1
Name: ksqldb
Version: 1.0.1
Summary: A simple Python wrapper for the KSQLdb REST API
Author: Victor Grosu
License: MIT License
Project-URL: repository, https://github.com/Erachter/ksqldb
Keywords: ksql,ksqldb,kafka
Classifier: License :: OSI Approved :: MIT License
Classifier: Programming Language :: Python
Classifier: Programming Language :: Python :: 3
Requires-Python: >=3.7
License-File: LICENSE
